[
  {
    "timestamp": "2026-03-11T05:13:30.151806",
    "match_id": 1522575,
    "home_team": "Monterrey",
    "away_team": "Cruz Azul",
    "type": "live",
    "predicted_total": 5.869565217391304,
    "total_range": "4+ голов",
    "first_goal_minute": 25,
    "next_goal_minute": 56,
    "attack_potential": "Высокий",
    "match_minute": 46,
    "current_score": "2:1",
    "recommendations": [
      "📊 Удары: 17 (6:11, в створ: 8)",
      "🎯 В створ: 4:4 (точность 47.1%)",
      "📈 Владение: 57% / 43%",
      "🚩 Угловые: 2:2",
      "⚽ Следующий гол ожидается ~56'"
    ]
  },
  {
    "timestamp": "2026-03-11T05:13:30.678586",
    "match_id": 1493348,
    "home_team": "Guadalajara W",
    "away_team": "América W",
    "type": "live",
    "predicted_total": 2.8723404255319145,
    "total_range": "2-3 гола",
    "first_goal_minute": null,
    "next_goal_minute": 72,
    "attack_potential": "Низкий",
    "match_minute": 47,
    "current_score": "0:0",
    "recommendations": [
      "📊 Удары: 0 (0:0, в створ: 0)",
      "🎯 В створ: 0:0",
      "📈 Владение: 50% / 50%",
      "🚩 Угловые: 0:0",
      "🛑 Очень низкая активность",
      "⚽ Следующий гол ожидается ~72'"
    ]
  },
  {
    "timestamp": "2026-03-11T05:13:57.190343",
    "match_id": 1491964,
    "home_team": "Newells Old Boys",
    "away_team": "Platense",
    "type": "live",
    "predicted_total": 1.6981132075471697,
    "total_range": "1-2 гола",
    "first_goal_minute": 23,
    "next_goal_minute": null,
    "attack_potential": "Средний",
    "match_minute": 53,
    "current_score": "1:0",
    "recommendations": [
      "📊 Удары: 13 (4:9, в створ: 5)",
      "🎯 В створ: 2:3 (точность 38.5%)",
      "📈 Владение: 35% / 65%",
      "🚩 Угловые: 1:1"
    ]
  },
  {
    "timestamp": "2026-03-11T05:13:57.891004",
    "match_id": 1491965,
    "home_team": "Sarmiento Junin",
    "away_team": "Racing Club",
    "type": "live",
    "predicted_total": 1.1886792452830188,
    "total_range": "0-1 гол",
    "first_goal_minute": null,
    "next_goal_minute": 75,
    "attack_potential": "Низкий",
    "match_minute": 53,
    "current_score": "0:0",
    "recommendations": [
      "📊 Удары: 7 (2:5, в створ: 2)",
      "🎯 В створ: 0:2 (точность 28.6%)",
      "📈 Владение: 44% / 56%",
      "🚩 Угловые: 0:2",
      "⚽ Следующий гол ожидается ~75'"
    ]
  },
  {
    "timestamp": "2026-03-11T05:13:58.448924",
    "match_id": 1511990,
    "home_team": "Rio Negro RR",
    "away_team": "Baré",
    "type": "live",
    "predicted_total": 6.0,
    "total_range": "4+ голов",
    "first_goal_minute": 17,
    "next_goal_minute": 56,
    "attack_potential": "Низкий",
    "match_minute": 45,
    "current_score": "0:4",
    "recommendations": [
      "📊 Удары: 0 (0:0, в створ: 0)",
      "🎯 В створ: 0:0",
      "📈 Владение: 50% / 50%",
      "🚩 Угловые: 0:0",
      "⚽ Следующий гол ожидается ~56'"
    ]
  },
  {
    "timestamp": "2026-03-11T05:13:59.060621",
    "match_id": 1522575,
    "home_team": "Monterrey",
    "away_team": "Cruz Azul",
    "type": "live",
    "predicted_total": 5.744680851063829,
    "total_range": "4+ голов",
    "first_goal_minute": 25,
    "next_goal_minute": 57,
    "attack_potential": "Высокий",
    "match_minute": 47,
    "current_score": "2:1",
    "recommendations": [
      "📊 Удары: 17 (6:11, в створ: 8)",
      "🎯 В створ: 4:4 (точность 47.1%)",
      "📈 Владение: 57% / 43%",
      "🚩 Угловые: 2:2",
      "⚽ Следующий гол ожидается ~57'"
    ]
  },
  {
    "timestamp": "2026-03-11T05:13:59.662468",
    "match_id": 1493348,
    "home_team": "Guadalajara W",
    "away_team": "América W",
    "type": "live",
    "predicted_total": 2.8125,
    "total_range": "2-3 гола",
    "first_goal_minute": null,
    "next_goal_minute": 73,
    "attack_potential": "Низкий",
    "match_minute": 48,
    "current_score": "0:0",
    "recommendations": [
      "📊 Удары: 0 (0:0, в створ: 0)",
      "🎯 В створ: 0:0",
      "📈 Владение: 50% / 50%",
      "🚩 Угловые: 0:0",
      "🛑 Очень низкая активность",
      "⚽ Следующий гол ожидается ~73'"
    ]
  },
  {
    "timestamp": "2026-03-11T05:14:00.313504",
    "match_id": 1505956,
    "home_team": "Junior",
    "away_team": "Atletico Nacional",
    "type": "live",
    "predicted_total": 0.8181818181818183,
    "total_range": "0-1 гол",
    "first_goal_minute": 4,
    "next_goal_minute": null,
    "attack_potential": "Низкий",
    "match_minute": 44,
    "current_score": "0:0",
    "recommendations": [
      "📊 Удары: 4 (1:3, в створ: 2)",
      "🎯 В створ: 1:1 (точность 50.0%)",
      "📈 Владение: 35% / 65%",
      "🚩 Угловые: 0:1"
    ]
  },
  {
    "timestamp": "2026-03-11T05:14:00.959957",
    "match_id": 1526644,
    "home_team": "Atlético Choloma",
    "away_team": "CD Marathon",
    "type": "live",
    "predicted_total": 2.0454545454545454,
    "total_range": "1-2 гола",
    "first_goal_minute": 43,
    "next_goal_minute": 88,
    "attack_potential": "Низкий",
    "match_minute": 44,
    "current_score": "0:1",
    "recommendations": [
      "📊 Удары: 6 (3:3, в створ: 3)",
      "🎯 В створ: 1:2 (точность 50.0%)",
      "📈 Владение: 49% / 51%",
      "🚩 Угловые: 1:2",
      "⚽ Следующий гол ожидается ~88'"
    ]
  },
  {
    "timestamp": "2026-03-11T05:14:26.324620",
    "match_id": 1492156,
    "home_team": "Mirassol",
    "away_team": "Santos",
    "type": "live",
    "predicted_total": 3.292682926829268,
    "total_range": "3-4 гола",
    "first_goal_minute": 21,
    "next_goal_minute": null,
    "attack_potential": "Высокий",
    "match_minute": 82,
    "current_score": "2:1",
    "recommendations": [
      "📊 Удары: 28 (17:11, в створ: 7)",
      "🎯 В створ: 7:0 (точность 25.0%)",
      "📈 Владение: 54% / 46%",
      "🚩 Угловые: 2:6",
      "⚽ Очень высокая активность, высокая вероятность голов"
    ]
  },
  {
    "timestamp": "2026-03-11T05:14:27.047711",
    "match_id": 1527881,
    "home_team": "Botafogo",
    "away_team": "Barcelona SC",
    "type": "live",
    "predicted_total": 1.0843373493975905,
    "total_range": "0-1 гол",
    "first_goal_minute": 8,
    "next_goal_minute": null,
    "attack_potential": "Высокий",
    "match_minute": 83,
    "current_score": "0:1",
    "recommendations": [
      "📊 Удары: 27 (20:7, в створ: 5)",
      "🎯 В створ: 3:2 (точность 18.5%)",
      "📈 Владение: 80% / 20%",
      "🚩 Угловые: 4:2",
      "⚽ Очень высокая активность, высокая вероятность голов"
    ]
  },
  {
    "timestamp": "2026-03-11T05:14:27.581744",
    "match_id": 1528145,
    "home_team": "Ponte Preta",
    "away_team": "Guarany de Bagé",
    "type": "live",
    "predicted_total": 1.0843373493975905,
    "total_range": "0-1 гол",
    "first_goal_minute": 48,
    "next_goal_minute": null,
    "attack_potential": "Средний",
    "match_minute": 83,
    "current_score": "1:0",
    "recommendations": [
      "📊 Удары: 9 (5:4, в створ: 2)",
      "🎯 В створ: 2:0 (точность 22.2%)",
      "📈 Владение: 58% / 42%",
      "🚩 Угловые: 5:4"
    ]
  },
  {
    "timestamp": "2026-03-11T05:14:28.149754",
    "match_id": 1491964,
    "home_team": "Newells Old Boys",
    "away_team": "Platense",
    "type": "live",
    "predicted_total": 1.6981132075471697,
    "total_range": "1-2 гола",
    "first_goal_minute": 23,
    "next_goal_minute": null,
    "attack_potential": "Средний",
    "match_minute": 53,
    "current_score": "1:0",
    "recommendations": [
      "📊 Удары: 13 (4:9, в створ: 5)",
      "🎯 В створ: 2:3 (точность 38.5%)",
      "📈 Владение: 35% / 65%",
      "🚩 Угловые: 1:1"
    ]
  },
  {
    "timestamp": "2026-03-11T05:14:28.760118",
    "match_id": 1491965,
    "home_team": "Sarmiento Junin",
    "away_team": "Racing Club",
    "type": "live",
    "predicted_total": 1.1886792452830188,
    "total_range": "0-1 гол",
    "first_goal_minute": null,
    "next_goal_minute": 75,
    "attack_potential": "Низкий",
    "match_minute": 53,
    "current_score": "0:0",
    "recommendations": [
      "📊 Удары: 7 (2:5, в створ: 2)",
      "🎯 В створ: 0:2 (точность 28.6%)",
      "📈 Владение: 44% / 56%",
      "🚩 Угловые: 0:2",
      "⚽ Следующий гол ожидается ~75'"
    ]
  },
  {
    "timestamp": "2026-03-11T05:14:29.405511",
    "match_id": 1511990,
    "home_team": "Rio Negro RR",
    "away_team": "Baré",
    "type": "live",
    "predicted_total": 6.0,
    "total_range": "4+ голов",
    "first_goal_minute": 17,
    "next_goal_minute": 56,
    "attack_potential": "Низкий",
    "match_minute": 45,
    "current_score": "0:4",
    "recommendations": [
      "📊 Удары: 0 (0:0, в створ: 0)",
      "🎯 В створ: 0:0",
      "📈 Владение: 50% / 50%",
      "🚩 Угловые: 0:0",
      "⚽ Следующий гол ожидается ~56'"
    ]
  },
  {
    "timestamp": "2026-03-11T05:14:29.988283",
    "match_id": 1522575,
    "home_team": "Monterrey",
    "away_team": "Cruz Azul",
    "type": "live",
    "predicted_total": 5.744680851063829,
    "total_range": "4+ голов",
    "first_goal_minute": 25,
    "next_goal_minute": 57,
    "attack_potential": "Высокий",
    "match_minute": 47,
    "current_score": "2:1",
    "recommendations": [
      "📊 Удары: 17 (6:11, в створ: 8)",
      "🎯 В створ: 4:4 (точность 47.1%)",
      "📈 Владение: 57% / 43%",
      "🚩 Угловые: 2:2",
      "⚽ Следующий гол ожидается ~57'"
    ]
  },
  {
    "timestamp": "2026-03-11T05:14:30.604383",
    "match_id": 1493348,
    "home_team": "Guadalajara W",
    "away_team": "América W",
    "type": "live",
    "predicted_total": 1.8367346938775508,
    "total_range": "1-2 гола",
    "first_goal_minute": null,
    "next_goal_minute": 54,
    "attack_potential": "Средний",
    "match_minute": 49,
    "current_score": "0:0",
    "recommendations": [
      "📊 Удары: 10 (3:7, в створ: 1)",
      "🎯 В створ: 0:1 (точность 10.0%)",
      "📈 Владение: 44% / 56%",
      "🚩 Угловые: 0:5",
      "⚽ Следующий гол ожидается ~54'"
    ]
  },
  {
    "timestamp": "2026-03-11T05:14:31.219639",
    "match_id": 1505956,
    "home_team": "Junior",
    "away_team": "Atletico Nacional",
    "type": "live",
    "predicted_total": 0.8181818181818183,
    "total_range": "0-1 гол",
    "first_goal_minute": 4,
    "next_goal_minute": null,
    "attack_potential": "Низкий",
    "match_minute": 44,
    "current_score": "0:0",
    "recommendations": [
      "📊 Удары: 4 (1:3, в створ: 2)",
      "🎯 В створ: 1:1 (точность 50.0%)",
      "📈 Владение: 35% / 65%",
      "🚩 Угловые: 0:1"
    ]
  },
  {
    "timestamp": "2026-03-11T05:14:57.603938",
    "match_id": 1491965,
    "home_team": "Sarmiento Junin",
    "away_team": "Racing Club",
    "type": "live",
    "predicted_total": 1.309090909090909,
    "total_range": "0-1 гол",
    "first_goal_minute": null,
    "next_goal_minute": 68,
    "attack_potential": "Низкий",
    "match_minute": 55,
    "current_score": "0:0",
    "recommendations": [
      "📊 Удары: 8 (3:5, в створ: 3)",
      "🎯 В створ: 1:2 (точность 37.5%)",
      "📈 Владение: 43% / 57%",
      "🚩 Угловые: 0:3",
      "⚽ Следующий гол ожидается ~68'"
    ]
  },
  {
    "timestamp": "2026-03-11T05:14:58.248038",
    "match_id": 1511990,
    "home_team": "Rio Negro RR",
    "away_team": "Baré",
    "type": "live",
    "predicted_total": 6.0,
    "total_range": "4+ голов",
    "first_goal_minute": 17,
    "next_goal_minute": 56,
    "attack_potential": "Низкий",
    "match_minute": 45,
    "current_score": "0:4",
    "recommendations": [
      "📊 Удары: 0 (0:0, в створ: 0)",
      "🎯 В створ: 0:0",
      "📈 Владение: 50% / 50%",
      "🚩 Угловые: 0:0",
      "⚽ Следующий гол ожидается ~56'"
    ]
  },
  {
    "timestamp": "2026-03-11T05:14:58.880315",
    "match_id": 1522575,
    "home_team": "Monterrey",
    "away_team": "Cruz Azul",
    "type": "live",
    "predicted_total": 5.625,
    "total_range": "4+ голов",
    "first_goal_minute": 25,
    "next_goal_minute": 59,
    "attack_potential": "Высокий",
    "match_minute": 48,
    "current_score": "2:1",
    "recommendations": [
      "📊 Удары: 19 (8:11, в створ: 8)",
      "🎯 В створ: 4:4 (точность 42.1%)",
      "📈 Владение: 57% / 43%",
      "🚩 Угловые: 3:2",
      "⚽ Следующий гол ожидается ~59'"
    ]
  },
  {
    "timestamp": "2026-03-11T05:14:59.532394",
    "match_id": 1493348,
    "home_team": "Guadalajara W",
    "away_team": "América W",
    "type": "live",
    "predicted_total": 1.8,
    "total_range": "1-2 гола",
    "first_goal_minute": null,
    "next_goal_minute": 55,
    "attack_potential": "Средний",
    "match_minute": 50,
    "current_score": "0:0",
    "recommendations": [
      "📊 Удары: 10 (3:7, в створ: 1)",
      "🎯 В створ: 0:1 (точность 10.0%)",
      "📈 Владение: 44% / 56%",
      "🚩 Угловые: 0:5",
      "⚽ Следующий гол ожидается ~55'"
    ]
  },
  {
    "timestamp": "2026-03-11T05:15:00.248044",
    "match_id": 1505956,
    "home_team": "Junior",
    "away_team": "Atletico Nacional",
    "type": "live",
    "predicted_total": 1.2,
    "total_range": "0-1 гол",
    "first_goal_minute": 4,
    "next_goal_minute": 75,
    "attack_potential": "Низкий",
    "match_minute": 45,
    "current_score": "0:0",
    "recommendations": [
      "📊 Удары: 6 (1:5, в створ: 3)",
      "🎯 В створ: 1:2 (точность 50.0%)",
      "📈 Владение: 36% / 64%",
      "🚩 Угловые: 0:1",
      "⚽ Следующий гол ожидается ~75'"
    ]
  },
  {
    "timestamp": "2026-03-11T05:15:00.776071",
    "match_id": 1526644,
    "home_team": "Atlético Choloma",
    "away_team": "CD Marathon",
    "type": "live",
    "predicted_total": 1.6,
    "total_range": "1-2 гола",
    "first_goal_minute": null,
    "next_goal_minute": 56,
    "attack_potential": "Средний",
    "match_minute": 45,
    "current_score": "0:0",
    "recommendations": [
      "📊 Удары: 8 (3:5, в створ: 5)",
      "🎯 В створ: 1:4 (точность 62.5%)",
      "📈 Владение: 47% / 53%",
      "🚩 Угловые: 1:2",
      "⚽ Следующий гол ожидается ~56'"
    ]
  },
  {
    "timestamp": "2026-03-11T05:15:26.136254",
    "match_id": 1492156,
    "home_team": "Mirassol",
    "away_team": "Santos",
    "type": "live",
    "predicted_total": 3.253012048192771,
    "total_range": "3-4 гола",
    "first_goal_minute": 21,
    "next_goal_minute": null,
    "attack_potential": "Высокий",
    "match_minute": 83,
    "current_score": "2:1",
    "recommendations": [
      "📊 Удары: 30 (17:13, в створ: 8)",
      "🎯 В створ: 7:1 (точность 26.7%)",
      "📈 Владение: 53% / 47%",
      "🚩 Угловые: 2:6",
      "⚽ Очень высокая активность, высокая вероятность голов"
    ]
  },
  {
    "timestamp": "2026-03-11T05:15:26.802512",
    "match_id": 1527881,
    "home_team": "Botafogo",
    "away_team": "Barcelona SC",
    "type": "live",
    "predicted_total": 1.0588235294117647,
    "total_range": "0-1 гол",
    "first_goal_minute": 8,
    "next_goal_minute": null,
    "attack_potential": "Высокий",
    "match_minute": 85,
    "current_score": "0:1",
    "recommendations": [
      "📊 Удары: 28 (21:7, в створ: 7)",
      "🎯 В створ: 5:2 (точность 25.0%)",
      "📈 Владение: 80% / 20%",
      "🚩 Угловые: 5:2",
      "⚽ Очень высокая активность, высокая вероятность голов"
    ]
  },
  {
    "timestamp": "2026-03-11T05:15:27.320563",
    "match_id": 1528145,
    "home_team": "Ponte Preta",
    "away_team": "Guarany de Bagé",
    "type": "live",
    "predicted_total": 1.0714285714285714,
    "total_range": "0-1 гол",
    "first_goal_minute": 48,
    "next_goal_minute": null,
    "attack_potential": "Средний",
    "match_minute": 84,
    "current_score": "1:0",
    "recommendations": [
      "📊 Удары: 9 (5:4, в створ: 2)",
      "🎯 В створ: 2:0 (точность 22.2%)",
      "📈 Владение: 58% / 42%",
      "🚩 Угловые: 5:4"
    ]
  },
  {
    "timestamp": "2026-03-11T05:15:27.949720",
    "match_id": 1491964,
    "home_team": "Newells Old Boys",
    "away_team": "Platense",
    "type": "live",
    "predicted_total": 1.6666666666666665,
    "total_range": "1-2 гола",
    "first_goal_minute": 23,
    "next_goal_minute": null,
    "attack_potential": "Средний",
    "match_minute": 54,
    "current_score": "1:0",
    "recommendations": [
      "📊 Удары: 13 (4:9, в створ: 5)",
      "🎯 В створ: 2:3 (точность 38.5%)",
      "📈 Владение: 37% / 63%",
      "🚩 Угловые: 1:1"
    ]
  },
  {
    "timestamp": "2026-03-11T05:15:28.558518",
    "match_id": 1491965,
    "home_team": "Sarmiento Junin",
    "away_team": "Racing Club",
    "type": "live",
    "predicted_total": 1.309090909090909,
    "total_range": "0-1 гол",
    "first_goal_minute": null,
    "next_goal_minute": 68,
    "attack_potential": "Низкий",
    "match_minute": 55,
    "current_score": "0:0",
    "recommendations": [
      "📊 Удары: 8 (3:5, в створ: 3)",
      "🎯 В створ: 1:2 (точность 37.5%)",
      "📈 Владение: 43% / 57%",
      "🚩 Угловые: 0:3",
      "⚽ Следующий гол ожидается ~68'"
    ]
  },
  {
    "timestamp": "2026-03-11T05:15:29.082092",
    "match_id": 1511990,
    "home_team": "Rio Negro RR",
    "away_team": "Baré",
    "type": "live",
    "predicted_total": 6.0,
    "total_range": "4+ голов",
    "first_goal_minute": 17,
    "next_goal_minute": 56,
    "attack_potential": "Низкий",
    "match_minute": 45,
    "current_score": "0:4",
    "recommendations": [
      "📊 Удары: 0 (0:0, в створ: 0)",
      "🎯 В створ: 0:0",
      "📈 Владение: 50% / 50%",
      "🚩 Угловые: 0:0",
      "⚽ Следующий гол ожидается ~56'"
    ]
  },
  {
    "timestamp": "2026-03-11T05:15:29.751308",
    "match_id": 1522575,
    "home_team": "Monterrey",
    "away_team": "Cruz Azul",
    "type": "live",
    "predicted_total": 5.625,
    "total_range": "4+ голов",
    "first_goal_minute": 25,
    "next_goal_minute": 59,
    "attack_potential": "Высокий",
    "match_minute": 48,
    "current_score": "2:1",
    "recommendations": [
      "📊 Удары: 19 (8:11, в створ: 8)",
      "🎯 В створ: 4:4 (точность 42.1%)",
      "📈 Владение: 57% / 43%",
      "🚩 Угловые: 3:2",
      "⚽ Следующий гол ожидается ~59'"
    ]
  },
  {
    "timestamp": "2026-03-11T05:15:30.406595",
    "match_id": 1493348,
    "home_team": "Guadalajara W",
    "away_team": "América W",
    "type": "live",
    "predicted_total": 1.8,
    "total_range": "1-2 гола",
    "first_goal_minute": null,
    "next_goal_minute": 55,
    "attack_potential": "Средний",
    "match_minute": 50,
    "current_score": "0:0",
    "recommendations": [
      "📊 Удары: 10 (3:7, в створ: 1)",
      "🎯 В створ: 0:1 (точность 10.0%)",
      "📈 Владение: 44% / 56%",
      "🚩 Угловые: 0:5",
      "⚽ Следующий гол ожидается ~55'"
    ]
  },
  {
    "timestamp": "2026-03-11T05:15:31.107527",
    "match_id": 1505956,
    "home_team": "Junior",
    "away_team": "Atletico Nacional",
    "type": "live",
    "predicted_total": 1.2,
    "total_range": "0-1 гол",
    "first_goal_minute": 4,
    "next_goal_minute": 75,
    "attack_potential": "Низкий",
    "match_minute": 45,
    "current_score": "0:0",
    "recommendations": [
      "📊 Удары: 6 (1:5, в створ: 3)",
      "🎯 В створ: 1:2 (точность 50.0%)",
      "📈 Владение: 36% / 64%",
      "🚩 Угловые: 0:1",
      "⚽ Следующий гол ожидается ~75'"
    ]
  },
  {
    "timestamp": "2026-03-11T05:15:31.750073",
    "match_id": 1526644,
    "home_team": "Atlético Choloma",
    "away_team": "CD Marathon",
    "type": "live",
    "predicted_total": 1.6,
    "total_range": "1-2 гола",
    "first_goal_minute": null,
    "next_goal_minute": 56,
    "attack_potential": "Средний",
    "match_minute": 45,
    "current_score": "0:0",
    "recommendations": [
      "📊 Удары: 8 (3:5, в створ: 5)",
      "🎯 В створ: 1:4 (точность 62.5%)",
      "📈 Владение: 47% / 53%",
      "🚩 Угловые: 1:2",
      "⚽ Следующий гол ожидается ~56'"
    ]
  },
  {
    "timestamp": "2026-03-11T05:15:57.596278",
    "match_id": 1491965,
    "home_team": "Sarmiento Junin",
    "away_team": "Racing Club",
    "type": "live",
    "predicted_total": 1.2857142857142858,
    "total_range": "0-1 гол",
    "first_goal_minute": null,
    "next_goal_minute": 70,
    "attack_potential": "Низкий",
    "match_minute": 56,
    "current_score": "0:0",
    "recommendations": [
      "📊 Удары: 8 (3:5, в створ: 3)",
      "🎯 В створ: 1:2 (точность 37.5%)",
      "📈 Владение: 43% / 57%",
      "🚩 Угловые: 0:3",
      "⚽ Следующий гол ожидается ~70'"
    ]
  },
  {
    "timestamp": "2026-03-11T05:15:58.289917",
    "match_id": 1511990,
    "home_team": "Rio Negro RR",
    "away_team": "Baré",
    "type": "live",
    "predicted_total": 6.0,
    "total_range": "4+ голов",
    "first_goal_minute": 17,
    "next_goal_minute": 56,
    "attack_potential": "Низкий",
    "match_minute": 45,
    "current_score": "0:4",
    "recommendations": [
      "📊 Удары: 0 (0:0, в створ: 0)",
      "🎯 В створ: 0:0",
      "📈 Владение: 50% / 50%",
      "🚩 Угловые: 0:0",
      "⚽ Следующий гол ожидается ~56'"
    ]
  },
  {
    "timestamp": "2026-03-11T05:15:58.998429",
    "match_id": 1522575,
    "home_team": "Monterrey",
    "away_team": "Cruz Azul",
    "type": "live",
    "predicted_total": 5.5102040816326525,
    "total_range": "4+ голов",
    "first_goal_minute": 25,
    "next_goal_minute": 60,
    "attack_potential": "Высокий",
    "match_minute": 49,
    "current_score": "2:1",
    "recommendations": [
      "📊 Удары: 19 (8:11, в створ: 8)",
      "🎯 В створ: 4:4 (точность 42.1%)",
      "📈 Владение: 57% / 43%",
      "🚩 Угловые: 3:2",
      "⚽ Следующий гол ожидается ~60'"
    ]
  },
  {
    "timestamp": "2026-03-11T05:15:59.532016",
    "match_id": 1493348,
    "home_team": "Guadalajara W",
    "away_team": "América W",
    "type": "live",
    "predicted_total": 1.7647058823529411,
    "total_range": "1-2 гола",
    "first_goal_minute": null,
    "next_goal_minute": 56,
    "attack_potential": "Средний",
    "match_minute": 51,
    "current_score": "0:0",
    "recommendations": [
      "📊 Удары: 10 (3:7, в створ: 1)",
      "🎯 В створ: 0:1 (точность 10.0%)",
      "📈 Владение: 43% / 57%",
      "🚩 Угловые: 0:5",
      "⚽ Следующий гол ожидается ~56'"
    ]
  },
  {
    "timestamp": "2026-03-11T05:16:00.180019",
    "match_id": 1505956,
    "home_team": "Junior",
    "away_team": "Atletico Nacional",
    "type": "live",
    "predicted_total": 1.2,
    "total_range": "0-1 гол",
    "first_goal_minute": 4,
    "next_goal_minute": 75,
    "attack_potential": "Низкий",
    "match_minute": 45,
    "current_score": "0:0",
    "recommendations": [
      "📊 Удары: 6 (1:5, в створ: 3)",
      "🎯 В створ: 1:2 (точность 50.0%)",
      "📈 Владение: 36% / 64%",
      "🚩 Угловые: 0:1",
      "⚽ Следующий гол ожидается ~75'"
    ]
  },
  {
    "timestamp": "2026-03-11T05:16:00.792773",
    "match_id": 1526644,
    "home_team": "Atlético Choloma",
    "away_team": "CD Marathon",
    "type": "live",
    "predicted_total": 1.6,
    "total_range": "1-2 гола",
    "first_goal_minute": null,
    "next_goal_minute": 56,
    "attack_potential": "Средний",
    "match_minute": 45,
    "current_score": "0:0",
    "recommendations": [
      "📊 Удары: 8 (3:5, в створ: 5)",
      "🎯 В створ: 1:4 (точность 62.5%)",
      "📈 Владение: 49% / 51%",
      "🚩 Угловые: 1:2",
      "⚽ Следующий гол ожидается ~56'"
    ]
  },
  {
    "timestamp": "2026-03-11T05:16:26.116587",
    "match_id": 1492156,
    "home_team": "Mirassol",
    "away_team": "Santos",
    "type": "live",
    "predicted_total": 3.214285714285714,
    "total_range": "3-4 гола",
    "first_goal_minute": 21,
    "next_goal_minute": null,
    "attack_potential": "Высокий",
    "match_minute": 84,
    "current_score": "2:1",
    "recommendations": [
      "📊 Удары: 30 (17:13, в створ: 8)",
      "🎯 В створ: 7:1 (точность 26.7%)",
      "📈 Владение: 53% / 47%",
      "🚩 Угловые: 2:6",
      "⚽ Очень высокая активность, высокая вероятность голов"
    ]
  },
  {
    "timestamp": "2026-03-11T05:16:26.808742",
    "match_id": 1527881,
    "home_team": "Botafogo",
    "away_team": "Barcelona SC",
    "type": "live",
    "predicted_total": 1.0465116279069768,
    "total_range": "0-1 гол",
    "first_goal_minute": 8,
    "next_goal_minute": null,
    "attack_potential": "Высокий",
    "match_minute": 86,
    "current_score": "0:1",
    "recommendations": [
      "📊 Удары: 28 (21:7, в створ: 7)",
      "🎯 В створ: 5:2 (точность 25.0%)",
      "📈 Владение: 80% / 20%",
      "🚩 Угловые: 5:2",
      "⚽ Очень высокая активность, высокая вероятность голов"
    ]
  },
  {
    "timestamp": "2026-03-11T05:16:27.864106",
    "match_id": 1528145,
    "home_team": "Ponte Preta",
    "away_team": "Guarany de Bagé",
    "type": "live",
    "predicted_total": 1.0588235294117647,
    "total_range": "0-1 гол",
    "first_goal_minute": 48,
    "next_goal_minute": null,
    "attack_potential": "Средний",
    "match_minute": 85,
    "current_score": "1:0",
    "recommendations": [
      "📊 Удары: 9 (5:4, в створ: 2)",
      "🎯 В створ: 2:0 (точность 22.2%)",
      "📈 Владение: 58% / 42%",
      "🚩 Угловые: 5:4"
    ]
  },
  {
    "timestamp": "2026-03-11T05:16:28.548942",
    "match_id": 1491964,
    "home_team": "Newells Old Boys",
    "away_team": "Platense",
    "type": "live",
    "predicted_total": 1.607142857142857,
    "total_range": "1-2 гола",
    "first_goal_minute": 23,
    "next_goal_minute": null,
    "attack_potential": "Средний",
    "match_minute": 56,
    "current_score": "1:0",
    "recommendations": [
      "📊 Удары: 13 (4:9, в створ: 5)",
      "🎯 В створ: 2:3 (точность 38.5%)",
      "📈 Владение: 37% / 63%",
      "🚩 Угловые: 1:1"
    ]
  },
  {
    "timestamp": "2026-03-11T05:16:29.217620",
    "match_id": 1491965,
    "home_team": "Sarmiento Junin",
    "away_team": "Racing Club",
    "type": "live",
    "predicted_total": 1.2857142857142858,
    "total_range": "0-1 гол",
    "first_goal_minute": null,
    "next_goal_minute": 70,
    "attack_potential": "Низкий",
    "match_minute": 56,
    "current_score": "0:0",
    "recommendations": [
      "📊 Удары: 8 (3:5, в створ: 3)",
      "🎯 В створ: 1:2 (точность 37.5%)",
      "📈 Владение: 43% / 57%",
      "🚩 Угловые: 0:3",
      "⚽ Следующий гол ожидается ~70'"
    ]
  },
  {
    "timestamp": "2026-03-11T05:16:29.856879",
    "match_id": 1511990,
    "home_team": "Rio Negro RR",
    "away_team": "Baré",
    "type": "live",
    "predicted_total": 6.0,
    "total_range": "4+ голов",
    "first_goal_minute": 17,
    "next_goal_minute": 56,
    "attack_potential": "Низкий",
    "match_minute": 45,
    "current_score": "0:4",
    "recommendations": [
      "📊 Удары: 0 (0:0, в створ: 0)",
      "🎯 В створ: 0:0",
      "📈 Владение: 50% / 50%",
      "🚩 Угловые: 0:0",
      "⚽ Следующий гол ожидается ~56'"
    ]
  },
  {
    "timestamp": "2026-03-11T05:16:30.575057",
    "match_id": 1522575,
    "home_team": "Monterrey",
    "away_team": "Cruz Azul",
    "type": "live",
    "predicted_total": 5.5102040816326525,
    "total_range": "4+ голов",
    "first_goal_minute": 25,
    "next_goal_minute": 60,
    "attack_potential": "Высокий",
    "match_minute": 49,
    "current_score": "2:1",
    "recommendations": [
      "📊 Удары: 19 (8:11, в створ: 8)",
      "🎯 В створ: 4:4 (точность 42.1%)",
      "📈 Владение: 57% / 43%",
      "🚩 Угловые: 3:2",
      "⚽ Следующий гол ожидается ~60'"
    ]
  },
  {
    "timestamp": "2026-03-11T05:16:31.095232",
    "match_id": 1493348,
    "home_team": "Guadalajara W",
    "away_team": "América W",
    "type": "live",
    "predicted_total": 1.7647058823529411,
    "total_range": "1-2 гола",
    "first_goal_minute": null,
    "next_goal_minute": 56,
    "attack_potential": "Средний",
    "match_minute": 51,
    "current_score": "0:0",
    "recommendations": [
      "📊 Удары: 10 (3:7, в створ: 1)",
      "🎯 В створ: 0:1 (точность 10.0%)",
      "📈 Владение: 43% / 57%",
      "🚩 Угловые: 0:5",
      "⚽ Следующий гол ожидается ~56'"
    ]
  },
  {
    "timestamp": "2026-03-11T05:16:31.742221",
    "match_id": 1505956,
    "home_team": "Junior",
    "away_team": "Atletico Nacional",
    "type": "live",
    "predicted_total": 1.2,
    "total_range": "0-1 гол",
    "first_goal_minute": 4,
    "next_goal_minute": 75,
    "attack_potential": "Низкий",
    "match_minute": 45,
    "current_score": "0:0",
    "recommendations": [
      "📊 Удары: 6 (1:5, в створ: 3)",
      "🎯 В створ: 1:2 (точность 50.0%)",
      "📈 Владение: 36% / 64%",
      "🚩 Угловые: 0:1",
      "⚽ Следующий гол ожидается ~75'"
    ]
  },
  {
    "timestamp": "2026-03-11T05:16:32.325479",
    "match_id": 1526644,
    "home_team": "Atlético Choloma",
    "away_team": "CD Marathon",
    "type": "live",
    "predicted_total": 1.6,
    "total_range": "1-2 гола",
    "first_goal_minute": null,
    "next_goal_minute": 56,
    "attack_potential": "Средний",
    "match_minute": 45,
    "current_score": "0:0",
    "recommendations": [
      "📊 Удары: 8 (3:5, в створ: 5)",
      "🎯 В створ: 1:4 (точность 62.5%)",
      "📈 Владение: 49% / 51%",
      "🚩 Угловые: 1:2",
      "⚽ Следующий гол ожидается ~56'"
    ]
  },
  {
    "timestamp": "2026-03-11T05:16:56.202692",
    "match_id": 1492156,
    "home_team": "Mirassol",
    "away_team": "Santos",
    "type": "live",
    "predicted_total": 3.176470588235294,
    "total_range": "3-4 гола",
    "first_goal_minute": 21,
    "next_goal_minute": null,
    "attack_potential": "Высокий",
    "match_minute": 85,
    "current_score": "2:1",
    "recommendations": [
      "📊 Удары: 30 (17:13, в створ: 8)",
      "🎯 В створ: 7:1 (точность 26.7%)",
      "📈 Владение: 53% / 47%",
      "🚩 Угловые: 2:6",
      "⚽ Очень высокая активность, высокая вероятность голов"
    ]
  },
  {
    "timestamp": "2026-03-11T05:16:57.826728",
    "match_id": 1491965,
    "home_team": "Sarmiento Junin",
    "away_team": "Racing Club",
    "type": "live",
    "predicted_total": 1.263157894736842,
    "total_range": "0-1 гол",
    "first_goal_minute": null,
    "next_goal_minute": 71,
    "attack_potential": "Низкий",
    "match_minute": 57,
    "current_score": "0:0",
    "recommendations": [
      "📊 Удары: 8 (3:5, в створ: 3)",
      "🎯 В створ: 1:2 (точность 37.5%)",
      "📈 Владение: 43% / 57%",
      "🚩 Угловые: 0:3",
      "⚽ Следующий гол ожидается ~71'"
    ]
  },
  {
    "timestamp": "2026-03-11T05:16:58.488131",
    "match_id": 1511990,
    "home_team": "Rio Negro RR",
    "away_team": "Baré",
    "type": "live",
    "predicted_total": 6.0,
    "total_range": "4+ голов",
    "first_goal_minute": 17,
    "next_goal_minute": 56,
    "attack_potential": "Низкий",
    "match_minute": 45,
    "current_score": "0:4",
    "recommendations": [
      "📊 Удары: 0 (0:0, в створ: 0)",
      "🎯 В створ: 0:0",
      "📈 Владение: 50% / 50%",
      "🚩 Угловые: 0:0",
      "⚽ Следующий гол ожидается ~56'"
    ]
  },
  {
    "timestamp": "2026-03-11T05:16:59.178123",
    "match_id": 1522575,
    "home_team": "Monterrey",
    "away_team": "Cruz Azul",
    "type": "live",
    "predicted_total": 5.3999999999999995,
    "total_range": "4+ голов",
    "first_goal_minute": 25,
    "next_goal_minute": 61,
    "attack_potential": "Высокий",
    "match_minute": 50,
    "current_score": "2:1",
    "recommendations": [
      "📊 Удары: 20 (8:12, в створ: 8)",
      "🎯 В створ: 4:4 (точность 40.0%)",
      "📈 Владение: 55% / 45%",
      "🚩 Угловые: 3:2",
      "⚽ Следующий гол ожидается ~61'"
    ]
  },
  {
    "timestamp": "2026-03-11T05:16:59.838942",
    "match_id": 1493348,
    "home_team": "Guadalajara W",
    "away_team": "América W",
    "type": "live",
    "predicted_total": 1.7307692307692308,
    "total_range": "1-2 гола",
    "first_goal_minute": null,
    "next_goal_minute": 57,
    "attack_potential": "Средний",
    "match_minute": 52,
    "current_score": "0:0",
    "recommendations": [
      "📊 Удары: 10 (3:7, в створ: 1)",
      "🎯 В створ: 0:1 (точность 10.0%)",
      "📈 Владение: 45% / 55%",
      "🚩 Угловые: 0:5",
      "⚽ Следующий гол ожидается ~57'"
    ]
  },
  {
    "timestamp": "2026-03-11T05:17:00.518780",
    "match_id": 1505956,
    "home_team": "Junior",
    "away_team": "Atletico Nacional",
    "type": "live",
    "predicted_total": 1.2,
    "total_range": "0-1 гол",
    "first_goal_minute": 4,
    "next_goal_minute": 75,
    "attack_potential": "Низкий",
    "match_minute": 45,
    "current_score": "0:0",
    "recommendations": [
      "📊 Удары: 6 (1:5, в створ: 3)",
      "🎯 В створ: 1:2 (точность 50.0%)",
      "📈 Владение: 34% / 66%",
      "🚩 Угловые: 0:4",
      "⚽ Следующий гол ожидается ~75'"
    ]
  },
  {
    "timestamp": "2026-03-11T05:17:01.145418",
    "match_id": 1526644,
    "home_team": "Atlético Choloma",
    "away_team": "CD Marathon",
    "type": "live",
    "predicted_total": 1.6,
    "total_range": "1-2 гола",
    "first_goal_minute": null,
    "next_goal_minute": 56,
    "attack_potential": "Средний",
    "match_minute": 45,
    "current_score": "0:0",
    "recommendations": [
      "📊 Удары: 8 (3:5, в створ: 5)",
      "🎯 В створ: 1:4 (точность 62.5%)",
      "📈 Владение: 49% / 51%",
      "🚩 Угловые: 1:2",
      "⚽ Следующий гол ожидается ~56'"
    ]
  },
  {
    "timestamp": "2026-03-11T05:17:26.149875",
    "match_id": 1492156,
    "home_team": "Mirassol",
    "away_team": "Santos",
    "type": "live",
    "predicted_total": 3.176470588235294,
    "total_range": "3-4 гола",
    "first_goal_minute": 21,
    "next_goal_minute": null,
    "attack_potential": "Высокий",
    "match_minute": 85,
    "current_score": "2:1",
    "recommendations": [
      "📊 Удары: 30 (17:13, в створ: 8)",
      "🎯 В створ: 7:1 (точность 26.7%)",
      "📈 Владение: 53% / 47%",
      "🚩 Угловые: 2:6",
      "⚽ Очень высокая активность, высокая вероятность голов"
    ]
  },
  {
    "timestamp": "2026-03-11T05:17:26.829548",
    "match_id": 1527881,
    "home_team": "Botafogo",
    "away_team": "Barcelona SC",
    "type": "live",
    "predicted_total": 1.0344827586206897,
    "total_range": "0-1 гол",
    "first_goal_minute": 8,
    "next_goal_minute": null,
    "attack_potential": "Высокий",
    "match_minute": 87,
    "current_score": "0:1",
    "recommendations": [
      "📊 Удары: 28 (21:7, в створ: 7)",
      "🎯 В створ: 5:2 (точность 25.0%)",
      "📈 Владение: 80% / 20%",
      "🚩 Угловые: 5:2",
      "⚽ Очень высокая активность, высокая вероятность голов"
    ]
  },
  {
    "timestamp": "2026-03-11T05:17:27.955497",
    "match_id": 1491964,
    "home_team": "Newells Old Boys",
    "away_team": "Platense",
    "type": "live",
    "predicted_total": 1.607142857142857,
    "total_range": "1-2 гола",
    "first_goal_minute": 23,
    "next_goal_minute": null,
    "attack_potential": "Средний",
    "match_minute": 56,
    "current_score": "1:0",
    "recommendations": [
      "📊 Удары: 13 (4:9, в створ: 5)",
      "🎯 В створ: 2:3 (точность 38.5%)",
      "📈 Владение: 37% / 63%",
      "🚩 Угловые: 1:1"
    ]
  },
  {
    "timestamp": "2026-03-11T05:17:28.684639",
    "match_id": 1491965,
    "home_team": "Sarmiento Junin",
    "away_team": "Racing Club",
    "type": "live",
    "predicted_total": 1.263157894736842,
    "total_range": "0-1 гол",
    "first_goal_minute": null,
    "next_goal_minute": 71,
    "attack_potential": "Низкий",
    "match_minute": 57,
    "current_score": "0:0",
    "recommendations": [
      "📊 Удары: 8 (3:5, в створ: 3)",
      "🎯 В створ: 1:2 (точность 37.5%)",
      "📈 Владение: 43% / 57%",
      "🚩 Угловые: 0:3",
      "⚽ Следующий гол ожидается ~71'"
    ]
  },
  {
    "timestamp": "2026-03-11T05:17:29.286980",
    "match_id": 1511990,
    "home_team": "Rio Negro RR",
    "away_team": "Baré",
    "type": "live",
    "predicted_total": 6.0,
    "total_range": "4+ голов",
    "first_goal_minute": 17,
    "next_goal_minute": 56,
    "attack_potential": "Низкий",
    "match_minute": 45,
    "current_score": "0:4",
    "recommendations": [
      "📊 Удары: 0 (0:0, в створ: 0)",
      "🎯 В створ: 0:0",
      "📈 Владение: 50% / 50%",
      "🚩 Угловые: 0:0",
      "⚽ Следующий гол ожидается ~56'"
    ]
  },
  {
    "timestamp": "2026-03-11T05:17:29.864759",
    "match_id": 1522575,
    "home_team": "Monterrey",
    "away_team": "Cruz Azul",
    "type": "live",
    "predicted_total": 5.3999999999999995,
    "total_range": "4+ голов",
    "first_goal_minute": 25,
    "next_goal_minute": 61,
    "attack_potential": "Высокий",
    "match_minute": 50,
    "current_score": "2:1",
    "recommendations": [
      "📊 Удары: 20 (8:12, в створ: 8)",
      "🎯 В створ: 4:4 (точность 40.0%)",
      "📈 Владение: 55% / 45%",
      "🚩 Угловые: 3:2",
      "⚽ Следующий гол ожидается ~61'"
    ]
  },
  {
    "timestamp": "2026-03-11T05:17:30.530584",
    "match_id": 1493348,
    "home_team": "Guadalajara W",
    "away_team": "América W",
    "type": "live",
    "predicted_total": 1.7307692307692308,
    "total_range": "1-2 гола",
    "first_goal_minute": null,
    "next_goal_minute": 57,
    "attack_potential": "Средний",
    "match_minute": 52,
    "current_score": "0:0",
    "recommendations": [
      "📊 Удары: 10 (3:7, в створ: 1)",
      "🎯 В створ: 0:1 (точность 10.0%)",
      "📈 Владение: 45% / 55%",
      "🚩 Угловые: 0:5",
      "⚽ Следующий гол ожидается ~57'"
    ]
  },
  {
    "timestamp": "2026-03-11T05:17:31.207287",
    "match_id": 1505956,
    "home_team": "Junior",
    "away_team": "Atletico Nacional",
    "type": "live",
    "predicted_total": 1.2,
    "total_range": "0-1 гол",
    "first_goal_minute": 4,
    "next_goal_minute": 75,
    "attack_potential": "Низкий",
    "match_minute": 45,
    "current_score": "0:0",
    "recommendations": [
      "📊 Удары: 6 (1:5, в створ: 3)",
      "🎯 В створ: 1:2 (точность 50.0%)",
      "📈 Владение: 34% / 66%",
      "🚩 Угловые: 0:4",
      "⚽ Следующий гол ожидается ~75'"
    ]
  },
  {
    "timestamp": "2026-03-11T05:17:31.869271",
    "match_id": 1526644,
    "home_team": "Atlético Choloma",
    "away_team": "CD Marathon",
    "type": "live",
    "predicted_total": 1.6,
    "total_range": "1-2 гола",
    "first_goal_minute": null,
    "next_goal_minute": 56,
    "attack_potential": "Средний",
    "match_minute": 45,
    "current_score": "0:0",
    "recommendations": [
      "📊 Удары: 8 (3:5, в створ: 5)",
      "🎯 В створ: 1:4 (точность 62.5%)",
      "📈 Владение: 49% / 51%",
      "🚩 Угловые: 1:2",
      "⚽ Следующий гол ожидается ~56'"
    ]
  },
  {
    "timestamp": "2026-03-11T05:17:56.131818",
    "match_id": 1492156,
    "home_team": "Mirassol",
    "away_team": "Santos",
    "type": "live",
    "predicted_total": 3.13953488372093,
    "total_range": "3-4 гола",
    "first_goal_minute": 21,
    "next_goal_minute": null,
    "attack_potential": "Высокий",
    "match_minute": 86,
    "current_score": "2:1",
    "recommendations": [
      "📊 Удары: 31 (17:14, в створ: 8)",
      "🎯 В створ: 7:1 (точность 25.8%)",
      "📈 Владение: 53% / 47%",
      "🚩 Угловые: 2:7",
      "⚽ Очень высокая активность, высокая вероятность голов"
    ]
  },
  {
    "timestamp": "2026-03-11T05:17:58.438823",
    "match_id": 1511990,
    "home_team": "Rio Negro RR",
    "away_team": "Baré",
    "type": "live",
    "predicted_total": 6.0,
    "total_range": "4+ голов",
    "first_goal_minute": 17,
    "next_goal_minute": 56,
    "attack_potential": "Низкий",
    "match_minute": 45,
    "current_score": "0:4",
    "recommendations": [
      "📊 Удары: 0 (0:0, в створ: 0)",
      "🎯 В створ: 0:0",
      "📈 Владение: 50% / 50%",
      "🚩 Угловые: 0:0",
      "⚽ Следующий гол ожидается ~56'"
    ]
  },
  {
    "timestamp": "2026-03-11T05:17:59.141661",
    "match_id": 1522575,
    "home_team": "Monterrey",
    "away_team": "Cruz Azul",
    "type": "live",
    "predicted_total": 5.294117647058823,
    "total_range": "4+ голов",
    "first_goal_minute": 25,
    "next_goal_minute": 63,
    "attack_potential": "Высокий",
    "match_minute": 51,
    "current_score": "2:1",
    "recommendations": [
      "📊 Удары: 20 (8:12, в створ: 8)",
      "🎯 В створ: 4:4 (точность 40.0%)",
      "📈 Владение: 55% / 45%",
      "🚩 Угловые: 3:2",
      "⚽ Следующий гол ожидается ~63'"
    ]
  },
  {
    "timestamp": "2026-03-11T05:17:59.769664",
    "match_id": 1493348,
    "home_team": "Guadalajara W",
    "away_team": "América W",
    "type": "live",
    "predicted_total": 1.903846153846154,
    "total_range": "1-2 гола",
    "first_goal_minute": null,
    "next_goal_minute": 57,
    "attack_potential": "Средний",
    "match_minute": 52,
    "current_score": "0:0",
    "recommendations": [
      "📊 Удары: 11 (4:7, в створ: 1)",
      "🎯 В створ: 0:1 (точность 9.1%)",
      "📈 Владение: 44% / 56%",
      "🚩 Угловые: 0:5",
      "⚽ Следующий гол ожидается ~57'"
    ]
  },
  {
    "timestamp": "2026-03-11T05:18:00.404009",
    "match_id": 1505956,
    "home_team": "Junior",
    "away_team": "Atletico Nacional",
    "type": "live",
    "predicted_total": 1.2,
    "total_range": "0-1 гол",
    "first_goal_minute": 4,
    "next_goal_minute": 75,
    "attack_potential": "Низкий",
    "match_minute": 45,
    "current_score": "0:0",
    "recommendations": [
      "📊 Удары: 6 (1:5, в створ: 3)",
      "🎯 В створ: 1:2 (точность 50.0%)",
      "📈 Владение: 34% / 66%",
      "🚩 Угловые: 0:4",
      "⚽ Следующий гол ожидается ~75'"
    ]
  },
  {
    "timestamp": "2026-03-11T05:18:00.982764",
    "match_id": 1526644,
    "home_team": "Atlético Choloma",
    "away_team": "CD Marathon",
    "type": "live",
    "predicted_total": 1.6,
    "total_range": "1-2 гола",
    "first_goal_minute": null,
    "next_goal_minute": 56,
    "attack_potential": "Средний",
    "match_minute": 45,
    "current_score": "0:0",
    "recommendations": [
      "📊 Удары: 8 (3:5, в створ: 5)",
      "🎯 В створ: 1:4 (точность 62.5%)",
      "📈 Владение: 49% / 51%",
      "🚩 Угловые: 1:2",
      "⚽ Следующий гол ожидается ~56'"
    ]
  },
  {
    "timestamp": "2026-03-11T05:18:26.220855",
    "match_id": 1492156,
    "home_team": "Mirassol",
    "away_team": "Santos",
    "type": "live",
    "predicted_total": 3.13953488372093,
    "total_range": "3-4 гола",
    "first_goal_minute": 21,
    "next_goal_minute": null,
    "attack_potential": "Высокий",
    "match_minute": 86,
    "current_score": "2:1",
    "recommendations": [
      "📊 Удары: 31 (17:14, в створ: 8)",
      "🎯 В створ: 7:1 (точность 25.8%)",
      "📈 Владение: 53% / 47%",
      "🚩 Угловые: 2:7",
      "⚽ Очень высокая активность, высокая вероятность голов"
    ]
  },
  {
    "timestamp": "2026-03-11T05:18:26.900602",
    "match_id": 1527881,
    "home_team": "Botafogo",
    "away_team": "Barcelona SC",
    "type": "live",
    "predicted_total": 1.0227272727272727,
    "total_range": "0-1 гол",
    "first_goal_minute": 8,
    "next_goal_minute": null,
    "attack_potential": "Высокий",
    "match_minute": 88,
    "current_score": "0:1",
    "recommendations": [
      "📊 Удары: 29 (21:8, в створ: 7)",
      "🎯 В створ: 5:2 (точность 24.1%)",
      "📈 Владение: 80% / 20%",
      "🚩 Угловые: 5:2",
      "⚽ Очень высокая активность, высокая вероятность голов"
    ]
  },
  {
    "timestamp": "2026-03-11T05:18:27.467548",
    "match_id": 1528145,
    "home_team": "Ponte Preta",
    "away_team": "Guarany de Bagé",
    "type": "live",
    "predicted_total": 1.0344827586206897,
    "total_range": "0-1 гол",
    "first_goal_minute": 48,
    "next_goal_minute": null,
    "attack_potential": "Средний",
    "match_minute": 87,
    "current_score": "1:0",
    "recommendations": [
      "📊 Удары: 9 (5:4, в створ: 2)",
      "🎯 В створ: 2:0 (точность 22.2%)",
      "📈 Владение: 58% / 42%",
      "🚩 Угловые: 5:4"
    ]
  },
  {
    "timestamp": "2026-03-11T05:18:28.585373",
    "match_id": 1491965,
    "home_team": "Sarmiento Junin",
    "away_team": "Racing Club",
    "type": "live",
    "predicted_total": 1.2413793103448276,
    "total_range": "0-1 гол",
    "first_goal_minute": null,
    "next_goal_minute": 72,
    "attack_potential": "Низкий",
    "match_minute": 58,
    "current_score": "0:0",
    "recommendations": [
      "📊 Удары: 8 (3:5, в створ: 3)",
      "🎯 В створ: 1:2 (точность 37.5%)",
      "📈 Владение: 44% / 56%",
      "🚩 Угловые: 0:3",
      "⚽ Следующий гол ожидается ~72'"
    ]
  },
  {
    "timestamp": "2026-03-11T05:18:29.189527",
    "match_id": 1511990,
    "home_team": "Rio Negro RR",
    "away_team": "Baré",
    "type": "live",
    "predicted_total": 6.0,
    "total_range": "4+ голов",
    "first_goal_minute": 17,
    "next_goal_minute": 56,
    "attack_potential": "Низкий",
    "match_minute": 45,
    "current_score": "0:4",
    "recommendations": [
      "📊 Удары: 0 (0:0, в створ: 0)",
      "🎯 В створ: 0:0",
      "📈 Владение: 50% / 50%",
      "🚩 Угловые: 0:0",
      "⚽ Следующий гол ожидается ~56'"
    ]
  },
  {
    "timestamp": "2026-03-11T05:18:29.865330",
    "match_id": 1522575,
    "home_team": "Monterrey",
    "away_team": "Cruz Azul",
    "type": "live",
    "predicted_total": 5.294117647058823,
    "total_range": "4+ голов",
    "first_goal_minute": 25,
    "next_goal_minute": 63,
    "attack_potential": "Высокий",
    "match_minute": 51,
    "current_score": "2:1",
    "recommendations": [
      "📊 Удары: 20 (8:12, в створ: 8)",
      "🎯 В створ: 4:4 (точность 40.0%)",
      "📈 Владение: 55% / 45%",
      "🚩 Угловые: 3:2",
      "⚽ Следующий гол ожидается ~63'"
    ]
  },
  {
    "timestamp": "2026-03-11T05:18:30.526465",
    "match_id": 1493348,
    "home_team": "Guadalajara W",
    "away_team": "América W",
    "type": "live",
    "predicted_total": 1.903846153846154,
    "total_range": "1-2 гола",
    "first_goal_minute": null,
    "next_goal_minute": 57,
    "attack_potential": "Средний",
    "match_minute": 52,
    "current_score": "0:0",
    "recommendations": [
      "📊 Удары: 11 (4:7, в створ: 1)",
      "🎯 В створ: 0:1 (точность 9.1%)",
      "📈 Владение: 44% / 56%",
      "🚩 Угловые: 0:5",
      "⚽ Следующий гол ожидается ~57'"
    ]
  },
  {
    "timestamp": "2026-03-11T05:18:31.115946",
    "match_id": 1505956,
    "home_team": "Junior",
    "away_team": "Atletico Nacional",
    "type": "live",
    "predicted_total": 1.2,
    "total_range": "0-1 гол",
    "first_goal_minute": 4,
    "next_goal_minute": 75,
    "attack_potential": "Низкий",
    "match_minute": 45,
    "current_score": "0:0",
    "recommendations": [
      "📊 Удары: 6 (1:5, в створ: 3)",
      "🎯 В створ: 1:2 (точность 50.0%)",
      "📈 Владение: 34% / 66%",
      "🚩 Угловые: 0:4",
      "⚽ Следующий гол ожидается ~75'"
    ]
  },
  {
    "timestamp": "2026-03-11T05:18:31.721383",
    "match_id": 1526644,
    "home_team": "Atlético Choloma",
    "away_team": "CD Marathon",
    "type": "live",
    "predicted_total": 1.6,
    "total_range": "1-2 гола",
    "first_goal_minute": null,
    "next_goal_minute": 56,
    "attack_potential": "Средний",
    "match_minute": 45,
    "current_score": "0:0",
    "recommendations": [
      "📊 Удары: 8 (3:5, в створ: 5)",
      "🎯 В створ: 1:4 (точность 62.5%)",
      "📈 Владение: 49% / 51%",
      "🚩 Угловые: 1:2",
      "⚽ Следующий гол ожидается ~56'"
    ]
  },
  {
    "timestamp": "2026-03-11T05:18:56.196145",
    "match_id": 1492156,
    "home_team": "Mirassol",
    "away_team": "Santos",
    "type": "live",
    "predicted_total": 3.103448275862069,
    "total_range": "3-4 гола",
    "first_goal_minute": 21,
    "next_goal_minute": null,
    "attack_potential": "Высокий",
    "match_minute": 87,
    "current_score": "2:1",
    "recommendations": [
      "📊 Удары: 31 (17:14, в створ: 8)",
      "🎯 В створ: 7:1 (точность 25.8%)",
      "📈 Владение: 53% / 47%",
      "🚩 Угловые: 2:7",
      "⚽ Очень высокая активность, высокая вероятность голов"
    ]
  },
  {
    "timestamp": "2026-03-11T05:18:56.770370",
    "match_id": 1527881,
    "home_team": "Botafogo",
    "away_team": "Barcelona SC",
    "type": "live",
    "predicted_total": 1.0112359550561798,
    "total_range": "0-1 гол",
    "first_goal_minute": 8,
    "next_goal_minute": null,
    "attack_potential": "Высокий",
    "match_minute": 89,
    "current_score": "0:1",
    "recommendations": [
      "📊 Удары: 29 (21:8, в створ: 7)",
      "🎯 В створ: 5:2 (точность 24.1%)",
      "📈 Владение: 80% / 20%",
      "🚩 Угловые: 5:2",
      "⚽ Очень высокая активность, высокая вероятность голов"
    ]
  },
  {
    "timestamp": "2026-03-11T05:18:58.311393",
    "match_id": 1511990,
    "home_team": "Rio Negro RR",
    "away_team": "Baré",
    "type": "live",
    "predicted_total": 6.0,
    "total_range": "4+ голов",
    "first_goal_minute": null,
    "next_goal_minute": 56,
    "attack_potential": "Низкий",
    "match_minute": 45,
    "current_score": "0:4",
    "recommendations": [
      "📊 Удары: 0 (0:0, в створ: 0)",
      "🎯 В створ: 0:0",
      "📈 Владение: 50% / 50%",
      "🚩 Угловые: 0:0",
      "⚽ Следующий гол ожидается ~56'"
    ]
  },
  {
    "timestamp": "2026-03-11T05:18:59.036002",
    "match_id": 1522575,
    "home_team": "Monterrey",
    "away_team": "Cruz Azul",
    "type": "live",
    "predicted_total": 5.09433962264151,
    "total_range": "4+ голов",
    "first_goal_minute": 25,
    "next_goal_minute": 65,
    "attack_potential": "Высокий",
    "match_minute": 53,
    "current_score": "2:1",
    "recommendations": [
      "📊 Удары: 20 (8:12, в створ: 8)",
      "🎯 В створ: 4:4 (точность 40.0%)",
      "📈 Владение: 55% / 45%",
      "🚩 Угловые: 3:2",
      "⚽ Следующий гол ожидается ~65'"
    ]
  },
  {
    "timestamp": "2026-03-11T05:18:59.603634",
    "match_id": 1493348,
    "home_team": "Guadalajara W",
    "away_team": "América W",
    "type": "live",
    "predicted_total": 1.8333333333333335,
    "total_range": "1-2 гола",
    "first_goal_minute": null,
    "next_goal_minute": 59,
    "attack_potential": "Средний",
    "match_minute": 54,
    "current_score": "0:0",
    "recommendations": [
      "📊 Удары: 11 (4:7, в створ: 1)",
      "🎯 В створ: 0:1 (точность 9.1%)",
      "📈 Владение: 44% / 56%",
      "🚩 Угловые: 0:5",
      "⚽ Следующий гол ожидается ~59'"
    ]
  },
  {
    "timestamp": "2026-03-11T05:19:00.270051",
    "match_id": 1505956,
    "home_team": "Junior",
    "away_team": "Atletico Nacional",
    "type": "live",
    "predicted_total": 2.0,
    "total_range": "1-2 гола",
    "first_goal_minute": 4,
    "next_goal_minute": 90,
    "attack_potential": "Средний",
    "match_minute": 45,
    "current_score": "0:1",
    "recommendations": [
      "📊 Удары: 7 (1:6, в створ: 3)",
      "🎯 В створ: 1:2 (точность 42.9%)",
      "📈 Владение: 33% / 67%",
      "🚩 Угловые: 0:4",
      "⚽ Следующий гол ожидается ~90'"
    ]
  },
  {
    "timestamp": "2026-03-11T05:19:00.913474",
    "match_id": 1526644,
    "home_team": "Atlético Choloma",
    "away_team": "CD Marathon",
    "type": "live",
    "predicted_total": 1.8,
    "total_range": "1-2 гола",
    "first_goal_minute": null,
    "next_goal_minute": 50,
    "attack_potential": "Средний",
    "match_minute": 45,
    "current_score": "0:0",
    "recommendations": [
      "📊 Удары: 9 (4:5, в створ: 5)",
      "🎯 В створ: 1:4 (точность 55.6%)",
      "📈 Владение: 49% / 51%",
      "🚩 Угловые: 1:2",
      "⚽ Следующий гол ожидается ~50'"
    ]
  },
  {
    "timestamp": "2026-03-11T05:19:26.181429",
    "match_id": 1492156,
    "home_team": "Mirassol",
    "away_team": "Santos",
    "type": "live",
    "predicted_total": 3.103448275862069,
    "total_range": "3-4 гола",
    "first_goal_minute": 21,
    "next_goal_minute": null,
    "attack_potential": "Высокий",
    "match_minute": 87,
    "current_score": "2:1",
    "recommendations": [
      "📊 Удары: 31 (17:14, в створ: 8)",
      "🎯 В створ: 7:1 (точность 25.8%)",
      "📈 Владение: 53% / 47%",
      "🚩 Угловые: 2:7",
      "⚽ Очень высокая активность, высокая вероятность голов"
    ]
  },
  {
    "timestamp": "2026-03-11T05:19:26.896064",
    "match_id": 1527881,
    "home_team": "Botafogo",
    "away_team": "Barcelona SC",
    "type": "live",
    "predicted_total": 1.0112359550561798,
    "total_range": "0-1 гол",
    "first_goal_minute": 8,
    "next_goal_minute": null,
    "attack_potential": "Высокий",
    "match_minute": 89,
    "current_score": "0:1",
    "recommendations": [
      "📊 Удары: 29 (21:8, в створ: 7)",
      "🎯 В створ: 5:2 (точность 24.1%)",
      "📈 Владение: 80% / 20%",
      "🚩 Угловые: 5:2",
      "⚽ Очень высокая активность, высокая вероятность голов"
    ]
  },
  {
    "timestamp": "2026-03-11T05:19:27.475645",
    "match_id": 1528145,
    "home_team": "Ponte Preta",
    "away_team": "Guarany de Bagé",
    "type": "live",
    "predicted_total": 1.0227272727272727,
    "total_range": "0-1 гол",
    "first_goal_minute": 48,
    "next_goal_minute": null,
    "attack_potential": "Средний",
    "match_minute": 88,
    "current_score": "1:0",
    "recommendations": [
      "📊 Удары: 10 (5:5, в створ: 2)",
      "🎯 В створ: 2:0 (точность 20.0%)",
      "📈 Владение: 58% / 42%",
      "🚩 Угловые: 5:4"
    ]
  },
  {
    "timestamp": "2026-03-11T05:19:28.176725",
    "match_id": 1491964,
    "home_team": "Newells Old Boys",
    "away_team": "Platense",
    "type": "live",
    "predicted_total": 1.5517241379310345,
    "total_range": "1-2 гола",
    "first_goal_minute": 23,
    "next_goal_minute": null,
    "attack_potential": "Средний",
    "match_minute": 58,
    "current_score": "1:0",
    "recommendations": [
      "📊 Удары: 14 (5:9, в створ: 5)",
      "🎯 В створ: 2:3 (точность 35.7%)",
      "📈 Владение: 37% / 63%",
      "🚩 Угловые: 1:2"
    ]
  },
  {
    "timestamp": "2026-03-11T05:19:28.720094",
    "match_id": 1491965,
    "home_team": "Sarmiento Junin",
    "away_team": "Racing Club",
    "type": "live",
    "predicted_total": 1.2203389830508475,
    "total_range": "0-1 гол",
    "first_goal_minute": null,
    "next_goal_minute": 73,
    "attack_potential": "Низкий",
    "match_minute": 59,
    "current_score": "0:0",
    "recommendations": [
      "📊 Удары: 8 (3:5, в створ: 3)",
      "🎯 В створ: 1:2 (точность 37.5%)",
      "📈 Владение: 44% / 56%",
      "🚩 Угловые: 0:3",
      "⚽ Следующий гол ожидается ~73'"
    ]
  },
  {
    "timestamp": "2026-03-11T05:19:29.329519",
    "match_id": 1511990,
    "home_team": "Rio Negro RR",
    "away_team": "Baré",
    "type": "live",
    "predicted_total": 6.0,
    "total_range": "4+ голов",
    "first_goal_minute": 17,
    "next_goal_minute": 56,
    "attack_potential": "Низкий",
    "match_minute": 45,
    "current_score": "0:4",
    "recommendations": [
      "📊 Удары: 0 (0:0, в створ: 0)",
      "🎯 В створ: 0:0",
      "📈 Владение: 50% / 50%",
      "🚩 Угловые: 0:0",
      "⚽ Следующий гол ожидается ~56'"
    ]
  },
  {
    "timestamp": "2026-03-11T05:19:29.960572",
    "match_id": 1522575,
    "home_team": "Monterrey",
    "away_team": "Cruz Azul",
    "type": "live",
    "predicted_total": 5.09433962264151,
    "total_range": "4+ голов",
    "first_goal_minute": 25,
    "next_goal_minute": 65,
    "attack_potential": "Высокий",
    "match_minute": 53,
    "current_score": "2:1",
    "recommendations": [
      "📊 Удары: 20 (8:12, в створ: 8)",
      "🎯 В створ: 4:4 (точность 40.0%)",
      "📈 Владение: 55% / 45%",
      "🚩 Угловые: 3:2",
      "⚽ Следующий гол ожидается ~65'"
    ]
  },
  {
    "timestamp": "2026-03-11T05:19:30.481435",
    "match_id": 1493348,
    "home_team": "Guadalajara W",
    "away_team": "América W",
    "type": "live",
    "predicted_total": 1.8333333333333335,
    "total_range": "1-2 гола",
    "first_goal_minute": null,
    "next_goal_minute": 59,
    "attack_potential": "Средний",
    "match_minute": 54,
    "current_score": "0:0",
    "recommendations": [
      "📊 Удары: 11 (4:7, в створ: 1)",
      "🎯 В створ: 0:1 (точность 9.1%)",
      "📈 Владение: 44% / 56%",
      "🚩 Угловые: 0:5",
      "⚽ Следующий гол ожидается ~59'"
    ]
  },
  {
    "timestamp": "2026-03-11T05:19:31.110312",
    "match_id": 1505956,
    "home_team": "Junior",
    "away_team": "Atletico Nacional",
    "type": "live",
    "predicted_total": 2.0,
    "total_range": "1-2 гола",
    "first_goal_minute": 4,
    "next_goal_minute": 90,
    "attack_potential": "Средний",
    "match_minute": 45,
    "current_score": "0:1",
    "recommendations": [
      "📊 Удары: 7 (1:6, в створ: 3)",
      "🎯 В створ: 1:2 (точность 42.9%)",
      "📈 Владение: 33% / 67%",
      "🚩 Угловые: 0:4",
      "⚽ Следующий гол ожидается ~90'"
    ]
  },
  {
    "timestamp": "2026-03-11T05:19:31.704357",
    "match_id": 1526644,
    "home_team": "Atlético Choloma",
    "away_team": "CD Marathon",
    "type": "live",
    "predicted_total": 1.8,
    "total_range": "1-2 гола",
    "first_goal_minute": null,
    "next_goal_minute": 50,
    "attack_potential": "Средний",
    "match_minute": 45,
    "current_score": "0:0",
    "recommendations": [
      "📊 Удары: 9 (4:5, в створ: 5)",
      "🎯 В створ: 1:4 (точность 55.6%)",
      "📈 Владение: 49% / 51%",
      "🚩 Угловые: 1:2",
      "⚽ Следующий гол ожидается ~50'"
    ]
  },
  {
    "timestamp": "2026-03-11T05:19:56.146885",
    "match_id": 1492156,
    "home_team": "Mirassol",
    "away_team": "Santos",
    "type": "live",
    "predicted_total": 3.103448275862069,
    "total_range": "3-4 гола",
    "first_goal_minute": 21,
    "next_goal_minute": null,
    "attack_potential": "Высокий",
    "match_minute": 87,
    "current_score": "2:1",
    "recommendations": [
      "📊 Удары: 31 (17:14, в створ: 8)",
      "🎯 В створ: 7:1 (точность 25.8%)",
      "📈 Владение: 53% / 47%",
      "🚩 Угловые: 2:7",
      "⚽ Очень высокая активность, высокая вероятность голов"
    ]
  },
  {
    "timestamp": "2026-03-11T05:19:56.710379",
    "match_id": 1527881,
    "home_team": "Botafogo",
    "away_team": "Barcelona SC",
    "type": "live",
    "predicted_total": 1.0112359550561798,
    "total_range": "0-1 гол",
    "first_goal_minute": 8,
    "next_goal_minute": null,
    "attack_potential": "Высокий",
    "match_minute": 89,
    "current_score": "0:1",
    "recommendations": [
      "📊 Удары: 29 (21:8, в створ: 7)",
      "🎯 В створ: 5:2 (точность 24.1%)",
      "📈 Владение: 81% / 19%",
      "🚩 Угловые: 6:2",
      "⚽ Очень высокая активность, высокая вероятность голов"
    ]
  }
]